eppy3000/__init__.py
eppy3000/epMunch.py
eppy3000/epj_mmapping.py
eppy3000/epjviewer.py
eppy3000/eppy3000.py
eppy3000/epschema.py
eppy3000/idfjsonconverter.py
eppy3000/installlocation.py
eppy3000/modelmaker.py
eppy3000/rawidf.py
eppy3000/readepj.py
eppy3000/dbm_functions/__init__.py
eppy3000/dbm_functions/json2dbm.py
eppy3000/dbm_functions/schemaindbm.py
eppy3000/experimental/__init__.py
eppy3000/experimental/hello.py
eppy3000/experimental/listfields.py
eppy3000/oldeppy/__init__.py
eppy3000/runner/__init__.py
eppy3000/runner/run_functions.py
eppy3000-0.1.15.dist-info/AUTHORS.rst
eppy3000-0.1.15.dist-info/LICENSE
eppy3000-0.1.15.dist-info/METADATA
eppy3000-0.1.15.dist-info/WHEEL
eppy3000-0.1.15.dist-info/top_level.txt
eppy3000-0.1.15.dist-info/RECORD
