Metadata-Version: 2.1
Name: eppy3000
Version: 0.1.15
Summary: E+ scripting using epJSON file format
Home-page: https://github.com/pyenergyplus/eppy3000
Author: Santosh Philip
Author-email: santosh@noemail.com
License: Mozilla Public License, v. 2.0
Keywords: eppy3000
Classifier: Development Status :: 2 - Pre-Alpha
Classifier: Intended Audience :: Developers
Classifier: License :: OSI Approved :: Mozilla Public License 2.0 (MPL 2.0)
Classifier: Natural Language :: English
Classifier: Programming Language :: Python :: 3.4
Classifier: Programming Language :: Python :: 3.5
Classifier: Programming Language :: Python :: 3.6
Classifier: Programming Language :: Python :: 3.7
License-File: LICENSE
License-File: AUTHORS.rst
Requires-Dist: munch
Requires-Dist: eppy
Requires-Dist: json2html
